{
  "schema_version": "1.0.0",
  "quality_threshold": 26,
  "below_streak_trigger": 3,
  "last_script_improved": null,
  "sec_ref": "17684-273-411-436",
  "owner": "Albert Lane | SovereignAudits™",
  "zones": {
    "city_hall": {
      "scores": [],
      "avg_score": 0.0,
      "best_score": 0,
      "best_iteration": 0,
      "below_threshold_streak": 0,
      "style_evolution_notes": ""
    },
    "gateway_district": {
      "scores": [],
      "avg_score": 0.0,
      "best_score": 0,
      "best_iteration": 0,
      "below_threshold_streak": 0,
      "style_evolution_notes": ""
    },
    "intelligence_core": {
      "scores": [],
      "avg_score": 0.0,
      "best_score": 0,
      "best_iteration": 0,
      "below_threshold_streak": 0,
      "style_evolution_notes": ""
    },
    "sovereign_quarters": {
      "scores": [],
      "avg_score": 0.0,
      "best_score": 0,
      "best_iteration": 0,
      "below_threshold_streak": 0,
      "style_evolution_notes": ""
    }
  },
  "global": {
    "total_scored": 0,
    "overall_avg": 0.0
  }
}
